brainio/__init__.py
brainio/assemblies.py
brainio/catalogs.py
brainio/fetch.py
brainio/lookup.py
brainio/packaging.py
brainio/stimuli.py
brainio/transform.py
brainio-test/brainio_test/__init__.py
brainio-test/brainio_test/entrypoint.py
docs/packaging.rst
brainscore_brainio-1.1.0.dist-info/LICENSE
brainscore_brainio-1.1.0.dist-info/METADATA
brainscore_brainio-1.1.0.dist-info/WHEEL
brainscore_brainio-1.1.0.dist-info/top_level.txt
brainscore_brainio-1.1.0.dist-info/RECORD
