Metadata-Version: 2.1
Name: brainscore-brainio
Version: 1.1.0
Summary: Data management for quantitative comparison of brains and brain-inspired systems
Author-email: Jon Prescott-Roy <jjpr@mit.edu>, Martin Schrimpf <mschrimpf@mit.edu>
License: MIT license
Project-URL: Homepage, https://github.com/brain-score/brainio
Keywords: BrainIO
Classifier: Development Status :: 2 - Pre-Alpha
Classifier: Intended Audience :: Developers
Classifier: License :: OSI Approved :: MIT License
Classifier: Natural Language :: English
Classifier: Programming Language :: Python :: 3.11
Requires-Python: >=3.11
License-File: LICENSE
Requires-Dist: six
Requires-Dist: boto3
Requires-Dist: tqdm
Requires-Dist: Pillow
Requires-Dist: entrypoints
Requires-Dist: numpy
Requires-Dist: pandas
Requires-Dist: xarray<2022.6
Requires-Dist: netcdf4
Provides-Extra: tests
Requires-Dist: pytest; extra == "tests"
Requires-Dist: imageio; extra == "tests"
Requires-Dist: moto; extra == "tests"
